{
  "__inputs": [],
  "__requires": [
    {
      "type": "datasource",
      "id": "prometheus",
      "name": "Prometheus",
      "version": "1.0.0"
    },
    {
      "type": "panel",
      "id": "timeseries",
      "name": "Time series",
      "version": ""
    },
    {
      "type": "panel",
      "id": "gauge",
      "name": "Gauge",
      "version": ""
    },
    {
      "type": "panel",
      "id": "stat",
      "name": "Stat",
      "version": ""
    }
  ],
  "annotations": {
    "list": [
      {
        "builtIn": 1,
        "datasource": { "type": "grafana", "uid": "-- Grafana --" },
        "enable": true,
        "hide": true,
        "iconColor": "rgba(0, 211, 255, 1)",
        "name": "Annotations & Alerts",
        "type": "dashboard"
      }
    ]
  },
  "description": "SpendWise observability: RED metrics (Rate, Error, Duration) + Infrastructure",
  "editable": true,
  "fiscalYearStartMonth": 0,
  "graphTooltip": 1,
  "id": null,
  "links": [],
  "refresh": "30s",
  "schemaVersion": 38,
  "tags": ["spendwise", "prometheus", "RED", "observability"],
  "templating": {
    "list": [
      {
        "current": {},
        "datasource": { "type": "prometheus", "uid": "spendwise-prometheus" },
        "definition": "label_values(up{job=~\"spendwise_backend|node_exporter\"}, instance)",
        "hide": 0,
        "includeAll": true,
        "multi": true,
        "name": "instance",
        "options": [],
        "query": {
          "query": "label_values(up{job=~\"spendwise_backend|node_exporter\"}, instance)",
          "refId": "StandardVariableQuery"
        },
        "refresh": 2,
        "regex": "",
        "sort": 1,
        "type": "query",
        "label": "Instance"
      }
    ]
  },
  "time": { "from": "now-1h", "to": "now" },
  "timepicker": {},
  "timezone": "browser",
  "title": "SpendWise – RED Metrics & Infrastructure",
  "uid": "spendwise-red-infra-v1",
  "version": 1,
  "panels": [

    {
      "collapsed": false,
      "gridPos": { "h": 1, "w": 24, "x": 0, "y": 0 },
      "id": 10,
      "title": "🔴 RED Metrics — Rate · Errors · Duration",
      "type": "row"
    },

    {
      "datasource": { "type": "prometheus", "uid": "spendwise-prometheus" },
      "description": "Total HTTP request throughput per second across all routes (5-minute window).",
      "fieldConfig": {
        "defaults": {
          "color": { "mode": "palette-classic" },
          "custom": {
            "axisBorderShow": false,
            "axisCenteredZero": false,
            "axisColorMode": "text",
            "axisLabel": "req/s",
            "axisPlacement": "auto",
            "barAlignment": 0,
            "drawStyle": "line",
            "fillOpacity": 15,
            "gradientMode": "opacity",
            "hideFrom": { "legend": false, "tooltip": false, "viz": false },
            "lineInterpolation": "smooth",
            "lineWidth": 2,
            "pointSize": 5,
            "scaleDistribution": { "type": "linear" },
            "showPoints": "never",
            "spanNulls": false,
            "stacking": { "group": "A", "mode": "none" },
            "thresholdsStyle": { "mode": "off" }
          },
          "mappings": [],
          "thresholds": {
            "mode": "absolute",
            "steps": [
              { "color": "green", "value": null }
            ]
          },
          "unit": "reqps"
        },
        "overrides": []
      },
      "gridPos": { "h": 8, "w": 8, "x": 0, "y": 1 },
      "id": 11,
      "options": {
        "legend": { "calcs": ["mean", "max", "lastNotNull"], "displayMode": "table", "placement": "bottom", "showLegend": true },
        "tooltip": { "mode": "multi", "sort": "desc" }
      },
      "targets": [
        {
          "datasource": { "type": "prometheus", "uid": "spendwise-prometheus" },
          "expr": "sum(rate(http_requests_total[5m]))",
          "legendFormat": "Request Rate",
          "refId": "A"
        }
      ],
      "title": "Request Rate (req/s)",
      "type": "timeseries"
    },

    {
      "datasource": { "type": "prometheus", "uid": "spendwise-prometheus" },
      "description": "Percentage of HTTP requests that resulted in an error (5xx or tracked error counter) over a 5-minute window.",
      "fieldConfig": {
        "defaults": {
          "color": {
            "mode": "thresholds"
          },
          "mappings": [],
          "max": 100,
          "min": 0,
          "thresholds": {
            "mode": "absolute",
            "steps": [
              { "color": "green",  "value": null },
              { "color": "yellow", "value": 1 },
              { "color": "orange", "value": 5 },
              { "color": "red",    "value": 10 }
            ]
          },
          "unit": "percent"
        },
        "overrides": []
      },
      "gridPos": { "h": 8, "w": 8, "x": 8, "y": 1 },
      "id": 12,
      "options": {
        "minVizHeight": 75,
        "minVizWidth": 75,
        "orientation": "auto",
        "reduceOptions": { "calcs": ["lastNotNull"], "fields": "", "values": false },
        "showThresholdLabels": false,
        "showThresholdMarkers": true,
        "sizing": "auto"
      },
      "targets": [
        {
          "datasource": { "type": "prometheus", "uid": "spendwise-prometheus" },
          "expr": "(sum(rate(http_errors_total[5m])) / sum(rate(http_requests_total[5m]))) * 100",
          "legendFormat": "Error Rate %",
          "refId": "A"
        }
      ],
      "title": "Error Rate (%)",
      "type": "gauge"
    },

    {
      "datasource": { "type": "prometheus", "uid": "spendwise-prometheus" },
      "description": "95th-percentile HTTP request duration — the latency experienced by the slowest 5% of requests (5-minute window).",
      "fieldConfig": {
        "defaults": {
          "color": { "mode": "palette-classic" },
          "custom": {
            "axisBorderShow": false,
            "axisCenteredZero": false,
            "axisColorMode": "text",
            "axisLabel": "latency",
            "axisPlacement": "auto",
            "barAlignment": 0,
            "drawStyle": "line",
            "fillOpacity": 15,
            "gradientMode": "opacity",
            "hideFrom": { "legend": false, "tooltip": false, "viz": false },
            "lineInterpolation": "smooth",
            "lineWidth": 2,
            "pointSize": 5,
            "scaleDistribution": { "type": "linear" },
            "showPoints": "never",
            "spanNulls": false,
            "stacking": { "group": "A", "mode": "none" },
            "thresholdsStyle": { "mode": "off" }
          },
          "mappings": [],
          "thresholds": {
            "mode": "absolute",
            "steps": [
              { "color": "green",  "value": null },
              { "color": "yellow", "value": 0.5 },
              { "color": "red",    "value": 1 }
            ]
          },
          "unit": "s"
        },
        "overrides": []
      },
      "gridPos": { "h": 8, "w": 8, "x": 16, "y": 1 },
      "id": 13,
      "options": {
        "legend": { "calcs": ["mean", "max", "lastNotNull"], "displayMode": "table", "placement": "bottom", "showLegend": true },
        "tooltip": { "mode": "multi", "sort": "desc" }
      },
      "targets": [
        {
          "datasource": { "type": "prometheus", "uid": "spendwise-prometheus" },
          "expr": "histogram_quantile(0.95, sum(rate(http_request_duration_seconds_bucket[5m])) by (le))",
          "legendFormat": "p95 Latency",
          "refId": "A"
        }
      ],
      "title": "P95 Request Latency (s)",
      "type": "timeseries"
    },

    {
      "collapsed": false,
      "gridPos": { "h": 1, "w": 24, "x": 0, "y": 9 },
      "id": 20,
      "title": "🖥️ Infrastructure — CPU · Memory",
      "type": "row"
    },

    {
      "datasource": { "type": "prometheus", "uid": "spendwise-prometheus" },
      "description": "Percentage of CPU time NOT spent idle — aggregated across all cores on the app server (5-minute rate).",
      "fieldConfig": {
        "defaults": {
          "color": { "mode": "palette-classic" },
          "custom": {
            "axisBorderShow": false,
            "axisCenteredZero": false,
            "axisColorMode": "text",
            "axisLabel": "CPU %",
            "axisPlacement": "auto",
            "barAlignment": 0,
            "drawStyle": "line",
            "fillOpacity": 20,
            "gradientMode": "opacity",
            "hideFrom": { "legend": false, "tooltip": false, "viz": false },
            "lineInterpolation": "smooth",
            "lineWidth": 2,
            "pointSize": 5,
            "scaleDistribution": { "type": "linear" },
            "showPoints": "never",
            "spanNulls": false,
            "stacking": { "group": "A", "mode": "none" },
            "thresholdsStyle": { "mode": "line+area" }
          },
          "mappings": [],
          "max": 100,
          "min": 0,
          "thresholds": {
            "mode": "absolute",
            "steps": [
              { "color": "green",  "value": null },
              { "color": "yellow", "value": 70 },
              { "color": "red",    "value": 90 }
            ]
          },
          "unit": "percent"
        },
        "overrides": []
      },
      "gridPos": { "h": 8, "w": 12, "x": 0, "y": 10 },
      "id": 21,
      "options": {
        "legend": { "calcs": ["mean", "max", "lastNotNull"], "displayMode": "table", "placement": "bottom", "showLegend": true },
        "tooltip": { "mode": "multi", "sort": "desc" }
      },
      "targets": [
        {
          "datasource": { "type": "prometheus", "uid": "spendwise-prometheus" },
          "expr": "100 - (avg by(instance)(rate(node_cpu_seconds_total{mode=\"idle\"}[5m])) * 100)",
          "legendFormat": "CPU Usage – {{ instance }}",
          "refId": "A"
        }
      ],
      "title": "CPU Usage (%)",
      "type": "timeseries"
    },

    {
      "datasource": { "type": "prometheus", "uid": "spendwise-prometheus" },
      "description": "Percentage of total RAM currently in use (100% minus percentage of MemAvailable).",
      "fieldConfig": {
        "defaults": {
          "color": { "mode": "palette-classic" },
          "custom": {
            "axisBorderShow": false,
            "axisCenteredZero": false,
            "axisColorMode": "text",
            "axisLabel": "Memory %",
            "axisPlacement": "auto",
            "barAlignment": 0,
            "drawStyle": "line",
            "fillOpacity": 20,
            "gradientMode": "opacity",
            "hideFrom": { "legend": false, "tooltip": false, "viz": false },
            "lineInterpolation": "smooth",
            "lineWidth": 2,
            "pointSize": 5,
            "scaleDistribution": { "type": "linear" },
            "showPoints": "never",
            "spanNulls": false,
            "stacking": { "group": "A", "mode": "none" },
            "thresholdsStyle": { "mode": "line+area" }
          },
          "mappings": [],
          "max": 100,
          "min": 0,
          "thresholds": {
            "mode": "absolute",
            "steps": [
              { "color": "green",  "value": null },
              { "color": "yellow", "value": 75 },
              { "color": "red",    "value": 90 }
            ]
          },
          "unit": "percent"
        },
        "overrides": []
      },
      "gridPos": { "h": 8, "w": 12, "x": 12, "y": 10 },
      "id": 22,
      "options": {
        "legend": { "calcs": ["mean", "max", "lastNotNull"], "displayMode": "table", "placement": "bottom", "showLegend": true },
        "tooltip": { "mode": "multi", "sort": "desc" }
      },
      "targets": [
        {
          "datasource": { "type": "prometheus", "uid": "spendwise-prometheus" },
          "expr": "(1 - (node_memory_MemAvailable_bytes / node_memory_MemTotal_bytes)) * 100",
          "legendFormat": "Memory Usage – {{ instance }}",
          "refId": "A"
        }
      ],
      "title": "Memory Usage (%)",
      "type": "timeseries"
    }

  ]
}
